pyTigerGraph/__init__.py
pyTigerGraph/datasets.py
pyTigerGraph/mcp.py
pyTigerGraph/mcp_client.py
pyTigerGraph/mcp_server.py
pyTigerGraph/pyTigerGraph.py
pyTigerGraph/pyTigerGraphAuth.py
pyTigerGraph/pyTigerGraphBase.py
pyTigerGraph/pyTigerGraphDataset.py
pyTigerGraph/pyTigerGraphEdge.py
pyTigerGraph/pyTigerGraphGSQL.py
pyTigerGraph/pyTigerGraphLoading.py
pyTigerGraph/pyTigerGraphPath.py
pyTigerGraph/pyTigerGraphQuery.py
pyTigerGraph/pyTigerGraphSchema.py
pyTigerGraph/pyTigerGraphUDT.py
pyTigerGraph/pyTigerGraphUtils.py
pyTigerGraph/pyTigerGraphVertex.py
pyTigerGraph/schema.py
pyTigerGraph/visualization.py
pyTigerGraph/ai/__init__.py
pyTigerGraph/ai/ai.py
pyTigerGraph/common/__init__.py
pyTigerGraph/common/auth.py
pyTigerGraph/common/base.py
pyTigerGraph/common/dataset.py
pyTigerGraph/common/edge.py
pyTigerGraph/common/exception.py
pyTigerGraph/common/gsql.py
pyTigerGraph/common/loading.py
pyTigerGraph/common/path.py
pyTigerGraph/common/query.py
pyTigerGraph/common/schema.py
pyTigerGraph/common/util.py
pyTigerGraph/common/vertex.py
pyTigerGraph/gds/__init__.py
pyTigerGraph/gds/dataloaders.py
pyTigerGraph/gds/featurizer.py
pyTigerGraph/gds/gds.py
pyTigerGraph/gds/metrics.py
pyTigerGraph/gds/splitters.py
pyTigerGraph/gds/trainer.py
pyTigerGraph/gds/utilities.py
pyTigerGraph/gds/gsql/dataloaders/edge_loader.gsql
pyTigerGraph/gds/gsql/dataloaders/edge_nei_loader.gsql
pyTigerGraph/gds/gsql/dataloaders/get_anchors.gsql
pyTigerGraph/gds/gsql/dataloaders/graph_loader.gsql
pyTigerGraph/gds/gsql/dataloaders/hgt_loader.gsql
pyTigerGraph/gds/gsql/dataloaders/neighbor_loader.gsql
pyTigerGraph/gds/gsql/dataloaders/nodepiece_loader.gsql
pyTigerGraph/gds/gsql/dataloaders/vertex_loader.gsql
pyTigerGraph/gds/gsql/splitters/random_anchor_selection.gsql
pyTigerGraph/gds/gsql/splitters/random_edge_split.gsql
pyTigerGraph/gds/gsql/splitters/random_vertex_split.gsql
pyTigerGraph/gds/models/GraphSAGE.py
pyTigerGraph/gds/models/NodePieceMLP.py
pyTigerGraph/gds/models/__init__.py
pytigergraph-1.9.1.dist-info/METADATA
pytigergraph-1.9.1.dist-info/WHEEL
pytigergraph-1.9.1.dist-info/top_level.txt
pytigergraph-1.9.1.dist-info/RECORD
