Metadata-Version: 2.4
Name: pyTigerGraph
Version: 1.9.1
Summary: Library to connect to TigerGraph databases
Home-page: https://docs.tigergraph.com/pytigergraph/current/intro/
Download-URL: 
Author: TigerGraph Inc.
Author-email: support@tigergraph.com
License: Apache 2
Project-URL: Bug Reports, https://github.com/tigergraph/pyTigerGraph/issues
Project-URL: Source, https://github.com/tigergraph/pyTigerGraph
Keywords: TigerGraph,Graph Database,Data Science,Machine Learning
Classifier: Development Status :: 5 - Production/Stable
Classifier: Intended Audience :: Developers
Classifier: Topic :: Software Development :: Build Tools
Classifier: License :: OSI Approved :: Apache Software License
Classifier: Programming Language :: Python :: 3
Classifier: Programming Language :: Python :: 3.4
Classifier: Programming Language :: Python :: 3.5
Classifier: Programming Language :: Python :: 3.6
Classifier: Programming Language :: Python :: 3.7
Classifier: Programming Language :: Python :: 3.8
Classifier: Programming Language :: Python :: 3.9
Classifier: Programming Language :: Python :: 3.10
Requires-Dist: validators
Requires-Dist: requests
Requires-Dist: httpx
Provides-Extra: gds
Requires-Dist: pandas; extra == "gds"
Requires-Dist: kafka-python; extra == "gds"
Requires-Dist: numpy; extra == "gds"
Requires-Dist: tqdm; extra == "gds"
Dynamic: author
Dynamic: author-email
Dynamic: classifier
Dynamic: description
Dynamic: description-content-type
Dynamic: home-page
Dynamic: keywords
Dynamic: license
Dynamic: project-url
Dynamic: provides-extra
Dynamic: requires-dist
Dynamic: summary
